<step title="BackgroundTrace" date="2025-12-30T08:43:12.651" instance="9e4b27" url="/api/publish" method="POST" >
  <step title="Creating temporary deployment - FetchDeploymentManager" date="2025-12-30T08:43:12.691" /><!-- duration: 2ms -->
  <step title="Creating temporary deployment" date="2025-12-30T08:43:12.695" /><!-- duration: 254ms -->
  <step title="Performing fetch based deployment" date="2025-12-30T08:43:12.990" >
    <step title="Cleaning up temp folders from previous zip deployments and extracting pushed zip file /tmp/zipdeploy/a25888c5-cbec-4dd4-bef3-e00db2248b31.zip (45.54 MB) to /tmp/zipdeploy/extracted" date="2025-12-30T08:43:14.472" >
      <step title="ChmodRecursive Process exited with total time taken in ms: 362" date="2025-12-30T08:43:36.744" /><!-- duration: 21ms -->
    </step><!-- duration: 22297ms -->
    <step title="Deployment timer started" date="2025-12-30T08:43:38.778" >
      <step title="DeploymentManager.Deploy(id:94b685d7-11bc-45da-8189-943c17848ca0)" date="2025-12-30T08:43:38.785" >
        <step title="Collecting changeset information" date="2025-12-30T08:43:38.796" /><!-- duration: 177ms -->
        <step title="Updating submodules" date="2025-12-30T08:43:38.980" /><!-- duration: 1146ms -->
        <step title="Determining deployment builder" date="2025-12-30T08:43:40.328" >
          <step title="Builder is OneDeployBuilder" date="2025-12-30T08:43:40.336" /><!-- duration: 2ms -->
        </step><!-- duration: 13ms -->
        <step title="PreDeployment: context.CleanOutputPath False" date="2025-12-30T08:43:40.390" >
          <step title="PreDeployment: context.OutputPath /home/site/wwwroot" date="2025-12-30T08:43:40.543" >
            <step title="Building" date="2025-12-30T08:43:40.668" >
              <step title="Executing external process" date="2025-12-30T08:43:41.323" type="process" path="starter.sh" arguments="/opt/Kudu/Scripts/absoluteTar.sh /tmp/zipdeploy/extracted/node_modules /tmp/zipdeploy/extracted/node_modules.tar.gz" /><!-- duration: 3602ms -->
              <step title="Executing external process" date="2025-12-30T08:43:45.206" type="process" path="starter.sh" arguments="/opt/Kudu/Scripts/parallel_rsync.sh /tmp/zipdeploy/extracted /home/site/wwwroot 8 /tmp/ False False node_modules " /><!-- duration: 2191ms -->
              <step title="Modified file to trigger a restart of the app container." date="2025-12-30T08:43:48.141" /><!-- duration: 3ms -->
              <step title="Skip function trigger and logicapp sync because function is not enabled." date="2025-12-30T08:43:48.159" /><!-- duration: 3ms -->
              <step title="Purge deployment items" date="2025-12-30T08:43:50.120" >
                <step title="Remove 580e074c-, Success, received at 12/28/2025 14:58:30" date="2025-12-30T08:43:50.182" /><!-- duration: 3ms -->
              </step><!-- duration: 68ms -->
            </step><!-- duration: 9593ms -->
          </step><!-- duration: 9723ms -->
          <step title="Cleaning up temp files" date="2025-12-30T08:43:50.268" /><!-- duration: 3ms -->
          <step title="Cleaning up temp files" date="2025-12-30T08:43:50.274" /><!-- duration: 506ms -->
          <step title="Reloading status file with latest updates" date="2025-12-30T08:43:50.806" >
            <step title="WebHooksManager.PublishEventAsync: PostDeployment" date="2025-12-30T08:43:50.809" /><!-- duration: 43ms -->
          </step><!-- duration: 50ms -->
          <step title="Cleaning up temporary deployment - fetch deployment was successful" date="2025-12-30T08:43:50.872" /><!-- duration: 2ms -->
        </step><!-- duration: 10556ms -->
      </step><!-- duration: 12174ms -->
